{
	"info": {
		"_postman_id": "51a396da-e7d6-4649-8b2c-29a95714ce07",
		"name": "Task Manager",
		"schema": "https://schema.getpostman.com/json/collection/v2.1.0/collection.json",
		"_exporter_id": "48495721",
		"_collection_link": "https://devdev-shq-2326296.postman.co/workspace/dev's-Workspace~ecf13be9-9255-4dcf-8fee-2984b872d1bd/collection/48495721-51a396da-e7d6-4649-8b2c-29a95714ce07?action=share&source=collection_link&creator=48495721"
	},
	"item": [
		{
			"name": "Tasks",
			"item": [
				{
					"name": "Create New Task",
					"request": {
						"method": "POST",
						"header": [],
						"body": {
							"mode": "raw",
							"raw": "{\r\n    \"title\": \"Creat Web3.\",\r\n    \"description\": \"Web3 using MERN stack\",\r\n    \"status\": \"PENDING\",\r\n    \"priority\": \"MEDIUM\",\r\n    \"due_date\": \"10/02/2026\",\r\n    \"tags\": \"MERN stack, Python, MongoDB\",\r\n    \"assigned_to\": \"Netesh Kumar Sharma\"\r\n}",
							"options": {
								"raw": {
									"language": "json"
								}
							}
						},
						"url": {
							"raw": "http://localhost:3000/task/create",
							"protocol": "http",
							"host": [
								"localhost"
							],
							"port": "3000",
							"path": [
								"task",
								"create"
							]
						}
					},
					"response": []
				},
				{
					"name": "Bulk Create Task",
					"request": {
						"method": "POST",
						"header": [],
						"url": {
							"raw": "http://localhost:4000/task/create/bulk",
							"protocol": "http",
							"host": [
								"localhost"
							],
							"port": "4000",
							"path": [
								"task",
								"create",
								"bulk"
							]
						}
					},
					"response": []
				},
				{
					"name": "Update Task",
					"request": {
						"method": "POST",
						"header": [],
						"body": {
							"mode": "raw",
							"raw": "{\r\n    \"id\": \"b7f5a8e7-4a50-4bb1-a3cb-db7643d83d15\",\r\n    \"status\": \"COMPLETED\"\r\n}",
							"options": {
								"raw": {
									"language": "json"
								}
							}
						},
						"url": {
							"raw": "http://localhost:4000/task/update",
							"protocol": "http",
							"host": [
								"localhost"
							],
							"port": "4000",
							"path": [
								"task",
								"update"
							]
						}
					},
					"response": []
				},
				{
					"name": "Delete Task",
					"request": {
						"method": "DELETE",
						"header": [],
						"body": {
							"mode": "raw",
							"raw": "{\r\n    \"id\": \"b7f5a8e7-4a50-4bb1-a3cb-db7643d83d15\"\r\n}",
							"options": {
								"raw": {
									"language": "json"
								}
							}
						},
						"url": {
							"raw": "http://localhost:4000/task/delete/",
							"protocol": "http",
							"host": [
								"localhost"
							],
							"port": "4000",
							"path": [
								"task",
								"delete",
								""
							]
						}
					},
					"response": []
				},
				{
					"name": "Get Task By Id",
					"request": {
						"method": "GET",
						"header": [],
						"url": {
							"raw": "http://localhost:4000/api/task?id=07288512-80b5-47d7-bd87-c1cb3b25379e",
							"protocol": "http",
							"host": [
								"localhost"
							],
							"port": "4000",
							"path": [
								"api",
								"task"
							],
							"query": [
								{
									"key": "id",
									"value": "07288512-80b5-47d7-bd87-c1cb3b25379e"
								}
							]
						}
					},
					"response": []
				},
				{
					"name": "Get All Tasks",
					"protocolProfileBehavior": {
						"disableBodyPruning": true
					},
					"request": {
						"method": "GET",
						"header": [],
						"body": {
							"mode": "raw",
							"raw": "",
							"options": {
								"raw": {
									"language": "json"
								}
							}
						},
						"url": {
							"raw": "http://localhost:4000/task/get-all-tasks",
							"protocol": "http",
							"host": [
								"localhost"
							],
							"port": "4000",
							"path": [
								"task",
								"get-all-tasks"
							]
						}
					},
					"response": []
				}
			]
		},
		{
			"name": "Comments",
			"item": [
				{
					"name": "Create Comment",
					"request": {
						"method": "POST",
						"header": [],
						"body": {
							"mode": "raw",
							"raw": "{\r\n    \"author\": \"Netesh Kumar Sharma\",\r\n    \"content\": \"Good Work!\",\r\n    \"taskId\": \"07288512-80b5-47d7-bd87-c1cb3b25379e\"\r\n}",
							"options": {
								"raw": {
									"language": "json"
								}
							}
						},
						"url": {
							"raw": "http://localhost:4000/comment/create",
							"protocol": "http",
							"host": [
								"localhost"
							],
							"port": "4000",
							"path": [
								"comment",
								"create"
							]
						}
					},
					"response": []
				},
				{
					"name": "Update By Id",
					"request": {
						"method": "POST",
						"header": [],
						"body": {
							"mode": "raw",
							"raw": "{\r\n    \"id\": \"f775d235-e630-427d-8183-4b978d265c26\",\r\n    \"author\": \"Netesh kr. Sharma\",\r\n    \"content\": \"Stong Backend!\"\r\n}",
							"options": {
								"raw": {
									"language": "json"
								}
							}
						},
						"url": {
							"raw": "http://localhost:4000/comment/update",
							"protocol": "http",
							"host": [
								"localhost"
							],
							"port": "4000",
							"path": [
								"comment",
								"update"
							]
						}
					},
					"response": []
				},
				{
					"name": "Delete Comment",
					"request": {
						"method": "DELETE",
						"header": [],
						"url": {
							"raw": "http://localhost:4000/comment/delete",
							"protocol": "http",
							"host": [
								"localhost"
							],
							"port": "4000",
							"path": [
								"comment",
								"delete"
							]
						}
					},
					"response": []
				},
				{
					"name": "Get Comment",
					"request": {
						"method": "GET",
						"header": [],
						"url": {
							"raw": "http://localhost:4000/comment/07288512-80b5-47d7-bd87-c1cb3b25379e/comments",
							"protocol": "http",
							"host": [
								"localhost"
							],
							"port": "4000",
							"path": [
								"comment",
								"07288512-80b5-47d7-bd87-c1cb3b25379e",
								"comments"
							]
						}
					},
					"response": []
				}
			]
		},
		{
			"name": "User",
			"item": [
				{
					"name": "Create User",
					"request": {
						"method": "POST",
						"header": [],
						"body": {
							"mode": "raw",
							"raw": "{\r\n    \"username\": \"testuser0\",\r\n    \"email\": \"testuser0@hmail.com\",\r\n    \"password\": \"testuser0\"\r\n}",
							"options": {
								"raw": {
									"language": "json"
								}
							}
						},
						"url": {
							"raw": "http://localhost:4000/user/create",
							"protocol": "http",
							"host": [
								"localhost"
							],
							"port": "4000",
							"path": [
								"user",
								"create"
							]
						}
					},
					"response": []
				},
				{
					"name": "User Login",
					"request": {
						"method": "POST",
						"header": [],
						"body": {
							"mode": "raw",
							"raw": "{\r\n    \"email\": \"testuser1@hmail.com\",\r\n    \"password\": \"testuser1\"\r\n}",
							"options": {
								"raw": {
									"language": "json"
								}
							}
						},
						"url": {
							"raw": "http://localhost:4000/user/login",
							"protocol": "http",
							"host": [
								"localhost"
							],
							"port": "4000",
							"path": [
								"user",
								"login"
							]
						}
					},
					"response": []
				},
				{
					"name": "User Logout",
					"request": {
						"method": "POST",
						"header": [],
						"url": {
							"raw": "http://localhost:4000/user/logout",
							"protocol": "http",
							"host": [
								"localhost"
							],
							"port": "4000",
							"path": [
								"user",
								"logout"
							]
						}
					},
					"response": []
				},
				{
					"name": "Current User Profile",
					"request": {
						"method": "GET",
						"header": [],
						"url": {
							"raw": "http://localhost:4000/user/currentuser",
							"protocol": "http",
							"host": [
								"localhost"
							],
							"port": "4000",
							"path": [
								"user",
								"currentuser"
							]
						}
					},
					"response": []
				}
			]
		}
	]
}